LangToken/__init__.py
LangToken/tokenizer.py
tests/__init__.py
tests/test_tokenizer.py
LangToken-0.1.3.dist-info/LICENSE
LangToken-0.1.3.dist-info/METADATA
LangToken-0.1.3.dist-info/WHEEL
LangToken-0.1.3.dist-info/top_level.txt
LangToken-0.1.3.dist-info/RECORD
