Metadata-Version: 2.1
Name: LangToken
Version: 0.1.3
Summary: Word Tokenizer to create each word into token and decode back
Home-page: https://github.com/ictorv/word_token
Author: S Victor Kumar
Author-email: victor.myid@gmail.com
Classifier: Programming Language :: Python :: 3
Classifier: License :: OSI Approved :: MIT License
Classifier: Operating System :: OS Independent
Requires-Python: >=3.6
License-File: LICENSE
